[
    {
        "redirect": true,
        "rule": "^u/([^/.]+)$",
        "replace": "/user/$1/"
    },
    {
        "redirect": true,
        "rule": "^user/([^/.]+)$",
        "replace": "/user/$1/"
    },
    {
        "redirect": true,
		"rule": "^u/([^/.]+)/$",
		"replace": "/user/$1/"
    },
    {
		"rule": "^user/([^/.]+)/$",
        "replace": "action=user&user=$1"
    },
    {
		"rule": "^r/([^/.]+)/comments/([^/.]+)/(.+)?$",
        "replace": "action=post&post=$2"
    },
    {
		"redirect": true,
        "rule": "^gallery/([\\d]+)$",
        "replace": "/gallery/$1/"
    },
    {
		"rule": "^gallery/([\\d]+)/$",
        "replace": "action=gallery&post=$1"
    },
    {
        "rule": "^images/$",
        "replace": "page=images"
    },
    {
        "rule": "^cache/([^/.]+)",
        "replace": "page=thumb&file=$1"
    },
    {
        "rule": "^stats/",
        "replace": "page=stats"
    }
]
